{
  "items": [
    {
      "name": "papy",
      "category": "Dairy",
      "isInCart": false,
      "id": 7
    },
    {
      "name": "papy",
      "category": "Dairy",
      "isInCart": false,
      "id": 9
    },
    {
      "name": "papy",
      "category": "Dairy",
      "isInCart": false,
      "id": 10
    },
    {
      "name": "papy",
      "category": "Dairy",
      "isInCart": false,
      "id": 11
    },
    {
      "name": "papy",
      "category": "Dairy",
      "isInCart": false,
      "id": 12
    },
    {
      "name": "papy",
      "category": "Produce",
      "isInCart": false,
      "id": 13
    },
    {
      "name": "kimemia",
      "category": "Produce",
      "isInCart": false,
      "id": 14
    }
  ]
}